CHANGES.rst
CONTRIBUTORS.rst
MANIFEST.in
README.rst
setup.py
docs/LICENSE.GPL
docs/LICENSE.txt
src/interlegis/__init__.py
src/interlegis.portalmodelo.theme.egg-info/PKG-INFO
src/interlegis.portalmodelo.theme.egg-info/SOURCES.txt
src/interlegis.portalmodelo.theme.egg-info/dependency_links.txt
src/interlegis.portalmodelo.theme.egg-info/entry_points.txt
src/interlegis.portalmodelo.theme.egg-info/namespace_packages.txt
src/interlegis.portalmodelo.theme.egg-info/not-zip-safe
src/interlegis.portalmodelo.theme.egg-info/requires.txt
src/interlegis.portalmodelo.theme.egg-info/top_level.txt
src/interlegis/portalmodelo/__init__.py
src/interlegis/portalmodelo/theme/__init__.py
src/interlegis/portalmodelo/theme/configure.zcml
src/interlegis/portalmodelo/theme/interfaces.py
src/interlegis/portalmodelo/theme/profiles.zcml
src/interlegis/portalmodelo/theme/testing.py
src/interlegis/portalmodelo/theme/themes.zcml
src/interlegis/portalmodelo/theme/browser/__init__.py
src/interlegis/portalmodelo/theme/browser/configure.zcml
src/interlegis/portalmodelo/theme/browser/imagewidget.py
src/interlegis/portalmodelo/theme/browser/interfaces.py
src/interlegis/portalmodelo/theme/browser/site.py
src/interlegis/portalmodelo/theme/browser/sitemap.py
src/interlegis/portalmodelo/theme/browser/stream.py
src/interlegis/portalmodelo/theme/browser/viewlets.py
src/interlegis/portalmodelo/theme/browser/contraste/__init__.py
src/interlegis/portalmodelo/theme/browser/contraste/configure.zcml
src/interlegis/portalmodelo/theme/browser/contraste/contraste.js
src/interlegis/portalmodelo/theme/browser/contraste/jquery.cookie.js
src/interlegis/portalmodelo/theme/browser/templates/colophon.pt
src/interlegis/portalmodelo/theme/browser/templates/footer.pt
src/interlegis/portalmodelo/theme/browser/templates/header.pt
src/interlegis/portalmodelo/theme/browser/templates/imagewidget.pt
src/interlegis/portalmodelo/theme/browser/templates/logo.pt
src/interlegis/portalmodelo/theme/browser/templates/stream_view.pt
src/interlegis/portalmodelo/theme/content/__init__.py
src/interlegis/portalmodelo/theme/content/stream.py
src/interlegis/portalmodelo/theme/jbot/Products.CMFPlone.skins.plone_templates.accessibility-info.pt
src/interlegis/portalmodelo/theme/jbot/plone.app.event.portlets.portlet_calendar.pt
src/interlegis/portalmodelo/theme/jbot/plone.app.portlets.portlets.news.pt
src/interlegis/portalmodelo/theme/jbot/plone.portlet.static.static.pt
